{"id":"litecoin","symbol":"ltc","name":"Litecoin","localization":{"en":"Litecoin","de":"Litecoin","es":"Litecoin","fr":"Litecoin","it":"Litecoin","pl":"Litecoin","ro":"Litecoin","hu":"Litecoin","nl":"Litecoin","pt":"Litecoin","sv":"Litecoin","vi":"Litecoin","tr":"Litecoin","ru":"Лайткоин","ja":"ライトコイン","zh":"莱特币","zh-tw":"萊特幣","ko":"라이트코인","ar":"لايتكوين","th":"Litecoin","id":"Litecoin"},"image":{"thumb":"https://assets.coingecko.com/coins/images/2/thumb/litecoin.png?1547033580","small":"https://assets.coingecko.com/coins/images/2/small/litecoin.png?1547033580"},"market_data":{"current_price":{"aud":null,"bdt":830.14954113276,"bhd":4.034684139408,"bmd":10.700604,"brl":null,"btc":0.02358,"cad":11.814589224,"chf":9.482329152,"cny":66.34651545,"dkk":null,"eur":7.734963906,"gbp":6.368764644,"hkd":83.393289738,"idr":null,"inr":null,"jpy":1093.904458272,"krw":11196.952898328,"ltc":1,"mmk":10304.40964264632,"mxn":null,"myr":null,"ngn":1721.216754088596,"nzd":null,"php":null,"pln":null,"rub":385.27472826,"sek":70.837085934,"sgd":13.516442712,"twd":325.929612348,"uah":122.4347058774,"usd":10.700604,"vef":67.32557872002,"vnd":225735.4833954331,"xag":null,"xau":null,"xdr":6.938106102,"zar":null},"market_cap":{"aud":null,"brl":null,"btc":null,"cad":null,"chf":null,"cny":null,"dkk":null,"eur":null,"gbp":null,"hkd":null,"idr":null,"inr":null,"jpy":null,"krw":null,"mxn":null,"myr":null,"ngn":47320982942.04606,"nzd":null,"php":null,"pln":null,"rub":null,"sek":null,"sgd":null,"twd":null,"uah":3366066832.9984503,"usd":294189037.0,"vnd":6206089345688.52,"xag":null,"xau":null,"xdr":null,"zar":null},"total_volume":{"aud":62715323.87995304,"bdt":4490666596.256189,"bhd":21825490.94294639,"bmd":57884564.84237291,"brl":130181098.022641,"btc":127555.233235727,"cad":63910631.215081714,"chf":51294347.18410914,"cny":358899289.76261723,"dkk":313944118.7822407,"eur":41842032.44697879,"gbp":34451622.54405733,"hkd":null,"idr":673237197022.6367,"inr":3531581320.344161,"jpy":5917440131.996885,"krw":null,"ltc":5409467.05834296,"mmk":55741364517.56682,"mxn":764048410.6119071,"myr":190275570.0363462,"ngn":9310865331.510254,"nzd":67835480.23069839,"php":2597132843.0724187,"pln":177063552.0440695,"rub":2084130950.9345055,"sek":null,"sgd":null,"twd":1763105501.334997,"uah":662306508.2417045,"usd":57884564.84237291,"vef":364195500.26982397,"vnd":1221108661326.7197,"xag":2951870.4520178707,"xau":44644.33163250445,"xdr":37531456.40605728,"zar":620208481.3704879}},"community_data":{"facebook_likes":null,"twitter_followers":14777,"reddit_average_posts_48h":0.0,"reddit_average_comments_48h":0.0,"reddit_subscribers":null,"reddit_accounts_active_48h":null},"developer_data":{"forks":634,"stars":914,"subscribers":233,"total_issues":151,"closed_issues":132,"pull_requests_merged":22,"pull_request_contributors":11,"code_additions_deletions_4_weeks":{"additions":null,"deletions":null},"commit_count_4_weeks":null},"public_interest_stats":{"alexa_rank":null,"bing_matches":null}}